funtracks/__init__.py
funtracks/exceptions.py
funtracks/actions/__init__.py
funtracks/actions/_base.py
funtracks/actions/action_history.py
funtracks/actions/add_delete_edge.py
funtracks/actions/add_delete_node.py
funtracks/actions/update_node_attrs.py
funtracks/actions/update_segmentation.py
funtracks/actions/update_track_id.py
funtracks/annotators/__init__.py
funtracks/annotators/_annotator_registry.py
funtracks/annotators/_compute_ious.py
funtracks/annotators/_edge_annotator.py
funtracks/annotators/_graph_annotator.py
funtracks/annotators/_regionprops_annotator.py
funtracks/annotators/_regionprops_extended.py
funtracks/annotators/_track_annotator.py
funtracks/data_model/__init__.py
funtracks/data_model/graph_attributes.py
funtracks/data_model/solution_tracks.py
funtracks/data_model/tracks.py
funtracks/data_model/tracks_controller.py
funtracks/features/__init__.py
funtracks/features/_edge_features.py
funtracks/features/_feature.py
funtracks/features/_feature_dict.py
funtracks/features/_node_features.py
funtracks/features/_regionprops_features.py
funtracks/features/_track_features.py
funtracks/import_export/__init__.py
funtracks/import_export/export_to_geff.py
funtracks/import_export/import_from_geff.py
funtracks/import_export/internal_format.py
funtracks/import_export/magic_imread.py
funtracks/user_actions/__init__.py
funtracks/user_actions/user_add_edge.py
funtracks/user_actions/user_add_node.py
funtracks/user_actions/user_delete_edge.py
funtracks/user_actions/user_delete_node.py
funtracks/user_actions/user_update_segmentation.py
funtracks-1.5.1.dist-info/licenses/LICENSE
funtracks-1.5.1.dist-info/METADATA
funtracks-1.5.1.dist-info/WHEEL
funtracks-1.5.1.dist-info/top_level.txt
funtracks-1.5.1.dist-info/RECORD
