Metadata-Version: 2.4
Name: funtracks
Version: 1.5.1
Summary: Cell tracking data model
Author-email: Caroline Malin-Mayor <malinmayorc@janelia.hhmi.org>
License: BSD 3-Clause License
Project-URL: Bug Tracker, https://github.com/funkelab/funtracks/issues
Project-URL: Documentation, https://funkelab.github.io/funtracks/
Classifier: Development Status :: 2 - Pre-Alpha
Classifier: Intended Audience :: Developers
Classifier: Intended Audience :: Science/Research
Classifier: License :: OSI Approved :: BSD License
Classifier: Operating System :: OS Independent
Classifier: Programming Language :: Python
Classifier: Programming Language :: Python :: 3
Classifier: Programming Language :: Python :: 3 :: Only
Classifier: Programming Language :: Python :: 3.10
Classifier: Programming Language :: Python :: 3.11
Classifier: Topic :: Scientific/Engineering :: Image Processing
Requires-Python: >=3.10
License-File: LICENSE
Requires-Dist: numpy<3,>=2
Requires-Dist: pydantic<3,>=2
Requires-Dist: networkx<4,>=3.4
Requires-Dist: psygnal>=0.14
Requires-Dist: scikit-image>=0.25
Requires-Dist: geff<1.1.3,>=1.1.1
Requires-Dist: dask>=2025.5.0
Dynamic: license-file
